jonway_picker/__init__.py
jonway_picker/jonway_picker.py
jonway_picker-0.1.dist-info/METADATA
jonway_picker-0.1.dist-info/WHEEL
jonway_picker-0.1.dist-info/top_level.txt
jonway_picker-0.1.dist-info/RECORD
