Metadata-Version: 2.2
Name: jonway_picker
Version: 0.1
Requires-Dist: shiny>=0.6.0
